carspy/__init__.py
carspy/cars_fit.py
carspy/cars_synth.py
carspy/convol_fcn.py
carspy/line_strength.py
carspy/utils.py
carspy/_constants/_CHI_NRS.json
carspy/_constants/_MOL_CONST.json
carspy/_constants/_UNIV_CONST.json
carspy/_constants/__init__.py
carspy/_constants/_reader.py
carspy-0.6.1.dist-info/AUTHORS.rst
carspy-0.6.1.dist-info/LICENSE
carspy-0.6.1.dist-info/METADATA
carspy-0.6.1.dist-info/WHEEL
carspy-0.6.1.dist-info/top_level.txt
carspy-0.6.1.dist-info/RECORD
